genomic_address_service/__init__.py
genomic_address_service/call.py
genomic_address_service/constants.py
genomic_address_service/main.py
genomic_address_service/mcluster.py
genomic_address_service/utils.py
genomic_address_service/version.py
genomic_address_service/classes/__init__.py
genomic_address_service/classes/assign.py
genomic_address_service/classes/multi_level_clustering.py
genomic_address_service/classes/neigbours.py
genomic_address_service/classes/reader.py
genomic_address_service/example/__init__.py
genomic_address_service-0.3.2.dist-info/licenses/LICENSE
genomic_address_service-0.3.2.dist-info/METADATA
genomic_address_service-0.3.2.dist-info/WHEEL
genomic_address_service-0.3.2.dist-info/entry_points.txt
genomic_address_service-0.3.2.dist-info/top_level.txt
genomic_address_service-0.3.2.dist-info/RECORD
