Metadata-Version: 2.4
Name: genomic_address_service
Version: 0.3.2
Summary: Genomic Address Service: De novo clustering and cluster address assignment
Home-page: https://github.com/phac-nml/genomic_address_service
Author: James Robertson
Author-email: james.robertson@phac-aspc.gc.ca
License: GPLv3
Keywords: cgMLST,wgMLST,outbreak,surveillance,clustering,nomenclature
Classifier: Development Status :: 4 - Beta
Classifier: Environment :: Console
Classifier: Intended Audience :: Science/Research
Classifier: Topic :: Scientific/Engineering
Classifier: Topic :: Scientific/Engineering :: Bio-Informatics
Classifier: Programming Language :: Python
Classifier: Programming Language :: Python :: 3.10
Classifier: Programming Language :: Python :: 3.11
Classifier: Programming Language :: Python :: 3.12
Classifier: Programming Language :: Python :: Implementation :: CPython
Classifier: Operating System :: POSIX :: Linux
Requires-Python: >=3.10.0,<3.13.0
License-File: LICENSE
Requires-Dist: numba<=0.61.2,>=0.59.1
Requires-Dist: numpy<2.0.0,>=1.26.4
Requires-Dist: tables>=3.9.1
Requires-Dist: six>=1.16.0
Requires-Dist: pandas<2.2.0,>=2.0.2
Requires-Dist: pytest>=8.3.3
Requires-Dist: scipy>=1.14.1
Requires-Dist: psutil>=6.1.0
Requires-Dist: scikit-bio>=0.4.2
Dynamic: author
Dynamic: author-email
Dynamic: classifier
Dynamic: home-page
Dynamic: keywords
Dynamic: license
Dynamic: license-file
Dynamic: requires-dist
Dynamic: requires-python
Dynamic: summary
